{"nodes": [{"id": "src_components_noemaorb_jsx", "label": "NoemaOrb.jsx", "file_type": "code", "source_file": "src/components/NoemaOrb.jsx", "source_location": "L1"}, {"id": "noemaorb_normalize", "label": "normalize()", "file_type": "code", "source_file": "src/components/NoemaOrb.jsx", "source_location": "L15"}, {"id": "noemaorb_cross", "label": "cross()", "file_type": "code", "source_file": "src/components/NoemaOrb.jsx", "source_location": "L19"}, {"id": "noemaorb_noemaorb", "label": "NoemaOrb()", "file_type": "code", "source_file": "src/components/NoemaOrb.jsx", "source_location": "L27"}], "edges": [{"source": "src_components_noemaorb_jsx", "target": "react", "relation": "imports_from", "confidence": "EXTRACTED", "source_file": "src/components/NoemaOrb.jsx", "source_location": "L1", "weight": 1.0}, {"source": "src_components_noemaorb_jsx", "target": "noemaorb_normalize", "relation": "contains", "confidence": "EXTRACTED", "source_file": "src/components/NoemaOrb.jsx", "source_location": "L15", "weight": 1.0}, {"source": "src_components_noemaorb_jsx", "target": "noemaorb_cross", "relation": "contains", "confidence": "EXTRACTED", "source_file": "src/components/NoemaOrb.jsx", "source_location": "L19", "weight": 1.0}, {"source": "src_components_noemaorb_jsx", "target": "noemaorb_noemaorb", "relation": "contains", "confidence": "EXTRACTED", "source_file": "src/components/NoemaOrb.jsx", "source_location": "L27", "weight": 1.0}]}